{
  "@context": "https://schema.org",
  "generated_at": "2026-06-10T10:47:28.539Z",
  "base_url": "https://nwooda.com",
  "currency": "USD",
  "count": 4,
  "products": [
    {
      "id": "1baf4f33-7702-4329-af1b-0126f7cdf4a6",
      "slug": "special-products-6muuvm",
      "name": "Special products",
      "name_translations": {
        "de": "Besondere Produkte",
        "en": "Special products",
        "fr": "Produits spéciaux",
        "he": "מוצרים מיוחדים"
      },
      "description": "<p>These products are more than just household items; they are statement pieces. They bridge the gap between the earthy, warm tones of the Mediterranean and the minimalist, polished finish of contemporary design. Whether used as a gift or a home upgrade, they symbolize luxury, roots, and creativity.</p>",
      "short_description": "These products are more than just household items; they are statement pieces. They bridge the gap between the earthy, warm tones of the Mediterranean and the minimalist, polished finish of contemporary design. Whether used as a gift or a home upgrade, they symbolize luxury, roots, and creativity.",
      "sku": null,
      "brand": null,
      "price": 0,
      "base_price": 0,
      "sale_price": null,
      "currency": "USD",
      "images": [
        "https://nwooda.com/assets/product-1774889450536-d0kz6.webp",
        "https://nwooda.com/assets/product-1774889455156-ctxl9u.webp",
        "https://nwooda.com/assets/product-1774889459799-n6t3cj.webp",
        "https://nwooda.com/assets/product-1774889464501-mve6pp.webp",
        "https://nwooda.com/assets/product-1774889551085-bx83sp.webp",
        "https://nwooda.com/assets/product-1774889554161-ow8r3k.webp"
      ],
      "in_stock": true,
      "stock_status": "in_stock",
      "url": "https://nwooda.com/product/special-products-6muuvm",
      "categories": [],
      "updated_at": "2026-05-26T08:05:53.151Z"
    },
    {
      "id": "0a20a953-b6f9-4802-9610-e40508c8bfaa",
      "slug": "mezuzahs-olive-wood-and-epoxy-w6nea7",
      "name": "Mezuzahs  olive wood and epoxy",
      "name_translations": {
        "de": "Mesusot aus Olivenholz und Epoxidharz",
        "en": "Mezuzahs  olive wood and epoxy",
        "fr": "Mezouzot en bois d'olivier et époxy",
        "he": "מזוזות עץ זית ואפוקסי"
      },
      "description": "<p>Mezuzahs that combine olive wood and epoxy (synthetic resin) are unique pieces of art that combine natural, raw materials with modern, luxurious design. This combination creates a \"Natural Wood Art\" look in which each mezuzah is one of a kind.</p>",
      "short_description": "Mezuzahs that combine olive wood and epoxy (synthetic resin) are unique pieces of art that combine natural, raw materials with modern, luxurious design. This combination creates a \"Natural Wood Art\" look in which each mezuzah is one of a kind.",
      "sku": null,
      "brand": null,
      "price": 79,
      "base_price": 90,
      "sale_price": 79,
      "currency": "USD",
      "images": [
        "https://nwooda.com/assets/product-1776962615785-mitcv.webp",
        "https://nwooda.com/assets/product-1779783514616-epf9me.webp",
        "https://nwooda.com/assets/product-1774888875251-f43754.webp",
        "https://nwooda.com/assets/product-1779783545594-l6ykbw.webp",
        "https://nwooda.com/assets/product-1780590862696-d548v.webp",
        "https://nwooda.com/assets/product-1774888879208-e1mey9.webp",
        "https://nwooda.com/assets/product-1774888883796-sp7kan.webp",
        "https://nwooda.com/assets/product-1774888889983-en2j7j.webp",
        "https://nwooda.com/assets/product-1774888895504-itf5b.webp",
        "https://nwooda.com/assets/product-1774888900551-8j0qvi.webp",
        "https://nwooda.com/assets/product-1774888905121-v81gd.webp",
        "https://nwooda.com/assets/product-1774888909322-pcaor.webp",
        "https://nwooda.com/assets/product-1776962688690-t3466a.webp",
        "https://nwooda.com/assets/product-1780590767791-kbi4wg.webp",
        "https://nwooda.com/assets/product-1780590829879-ni3lu7.webp",
        "https://nwooda.com/assets/product-1780590842152-35yz3q.webp"
      ],
      "in_stock": true,
      "stock_status": "in_stock",
      "url": "https://nwooda.com/product/mezuzahs-olive-wood-and-epoxy-w6nea7",
      "categories": [],
      "updated_at": "2026-06-04T16:40:49.436Z"
    },
    {
      "id": "4b95ce83-f33a-43a3-aa49-c1af09dcfae6",
      "slug": "olive-wood-cutting-bord-nf3hg3",
      "name": "olive wood cutting bord",
      "name_translations": {
        "de": "Olivenholz Schneidebrett",
        "en": "olive wood cutting bord",
        "fr": "planche à découper en bois d'olivier",
        "he": "קרש חיתוך מעץ זית"
      },
      "description": "<p>This cutting board is a <strong>high-end artisanal piece</strong> that blends the rustic, ancient beauty of natural olive wood with the sleek, modern aesthetic of liquid resin. Each board is a <strong>one-of-a-kind creation</strong>, as the resin follows the unique, organic contours of the specific wood slab used.</p>",
      "short_description": "This cutting board is a high-end artisanal piece that blends the rustic, ancient beauty of natural olive wood with the sleek, modern aesthetic of liquid resin. Each board is a one-of-a-kind creation, as the resin follows the unique, organic contours of the specific wood slab used.",
      "sku": null,
      "brand": null,
      "price": 250,
      "base_price": 320,
      "sale_price": 250,
      "currency": "USD",
      "images": [
        "https://nwooda.com/assets/product-1776962310065-tjdltt.webp",
        "https://nwooda.com/assets/product-1776962294519-tdpw9j.webp",
        "https://nwooda.com/assets/product-autofit-1776961958043-l6b3er.webp",
        "https://nwooda.com/assets/product-1774874739953-cpk9dd.webp",
        "https://nwooda.com/assets/product-1774874743661-6ju9ei.webp",
        "https://nwooda.com/assets/product-1774874747712-gnjlsj.webp",
        "https://nwooda.com/assets/product-1776961796989-xocbie.webp",
        "https://nwooda.com/assets/product-1776961811090-97rvgn.webp",
        "https://nwooda.com/assets/product-1776961866856-i0tpq.webp",
        "https://nwooda.com/assets/product-1780591317336-9lxxqn.webp",
        "https://nwooda.com/assets/product-1780591358559-rvselo.webp"
      ],
      "in_stock": true,
      "stock_status": "in_stock",
      "url": "https://nwooda.com/product/olive-wood-cutting-bord-nf3hg3",
      "categories": [],
      "updated_at": "2026-06-04T16:43:10.656Z"
    },
    {
      "id": "05ae8d26-1904-40c1-aa30-a82e2926a88d",
      "slug": "indian-rosewood-cutting-bord-nzusha",
      "name": "Indian Rosewood cutting bord",
      "name_translations": {
        "de": "Schneidebrett aus indischem Palisander",
        "en": "Indian Rosewood cutting bord",
        "fr": "Planche à découper en palissandre indien",
        "he": "קרש חיתוך מעץ סיסם הודי"
      },
      "description": "<p>Indian Rosewood cutting bord</p>",
      "short_description": null,
      "sku": null,
      "brand": null,
      "price": 250,
      "base_price": 320,
      "sale_price": 250,
      "currency": "USD",
      "images": [
        "https://nwooda.com/assets/product-1776961668415-qkui8.webp",
        "https://nwooda.com/assets/product-1774867288428-5ff1mg.webp",
        "https://nwooda.com/assets/product-1774867293223-tdzil.webp",
        "https://nwooda.com/assets/product-1776961709370-rdlalj.webp",
        "https://nwooda.com/assets/product-1776961726281-1jpbkn.webp",
        "https://nwooda.com/assets/product-1776961743082-5qw2oa.webp",
        "https://nwooda.com/assets/product-1780590513438-15v3sj.webp",
        "https://nwooda.com/assets/product-1780590521557-t6zi39.webp",
        "https://nwooda.com/assets/product-1780590529526-jgh0t.webp",
        "https://nwooda.com/assets/product-1780590538292-yzsrns.webp",
        "https://nwooda.com/assets/product-1780590546635-2sdu5.webp",
        "https://nwooda.com/assets/product-1780591269159-40zte.webp",
        "https://nwooda.com/assets/product-1780591277137-1wppj.webp"
      ],
      "in_stock": true,
      "stock_status": "in_stock",
      "url": "https://nwooda.com/product/indian-rosewood-cutting-bord-nzusha",
      "categories": [],
      "updated_at": "2026-06-04T16:41:36.013Z"
    }
  ]
}